{
  "SequenceId": 0,
  "DataVersion": 4,
  "DbType": 2,
  "ProjectOptions": {
    "GenerateSql": {
      "DatabaseOptions": {
        "CreateSchema": false,
        "DropSchema": false,
        "Databricks": {
          "DropSchemaActionType": 1
        },
        "GoogleBigQuery": {
          "DropSchemaActionType": 1
        }
      },
      "TableOptions": {
        "CreateTable": true,
        "DropTable": false
      },
      "QuotingOptions": {
        "Quoting": 1
      },
      "IndexOptions": {
        "CreatePKIndex": true,
        "CreateAKIndex": true,
        "CreateFKIndex": true,
        "CreateIEIndex": true,
        "DropPKIndex": false,
        "DropAKIndex": false,
        "DropFKIndex": false,
        "DropIEIndex": false,
        "Oracle": {
          "DropIndex": false,
          "CreateIndex": true
        },
        "Databricks": {
          "DropIndex": false,
          "CreateIndex": true
        },
        "ExternalDatabricks": {
          "DropIndex": false,
          "CreateIndex": true
        },
        "GoogleBigQuery": {
          "CreateIndex": true,
          "DropIndex": false
        }
      },
      "Snowflake": {
        "FileFormatOptions": {
          "CreateFileFormat": true,
          "DropFileFormat": false
        },
        "TagOptions": {
          "CreateTag": true,
          "DropTag": false,
          "ApplyTag": true
        }
      },
      "SafeScripts": false,
      "DomainOptions": {
        "CreateDomain": true,
        "DropDomain": false
      },
      "ViewOptions": {
        "CreateView": true,
        "DropView": false
      },
      "MaterializedViewOptions": {
        "CreateView": true,
        "DropView": false
      },
      "CodeOptions": {
        "CreateFunction": true,
        "DropFunction": false,
        "CreateProcedure": true,
        "DropProcedure": false
      },
      "SequenceOptions": {
        "CreateSequence": true,
        "DropSequence": false
      },
      "ExternalTableOptions": {
        "CreateTable": true,
        "DropTable": false
      },
      "PostgreSqlOptions": {
        "DropPartition": false,
        "CreatePartition": true
      }
    },
    "Notation": 1,
    "DefaultVirtualIdReferenceColor": null,
    "DefaultVirtualNonIdReferenceColor": null,
    "DefaultReferenceType": 2,
    "FormatType": 1
  },
  "DatabaseModel": {
    "Databases": {},
    "Schemas": {
      "be23f0a5-7b1d-4657-ac67-2220857ed45c": {
        "Id": "be23f0a5-7b1d-4657-ac67-2220857ed45c",
        "SchemaId": "00000000-0000-0000-0000-000000000000",
        "DatabaseId": null,
        "Name": "SAMPLEDB",
        "LogicalName": "SAMPLEDB",
        "Generate": true,
        "IsAutogeneratedName": null,
        "Comment": null,
        "Color": null,
        "MySql": {
          "Collation": null
        },
        "Snowflake": {
          "Transient": false,
          "WithManagedAccess": false,
          "DataRetentionTimeInDays": null,
          "Tags": {},
          "UseQuotes": false
        },
        "Oracle": {
          "User": null
        },
        "Databricks": {
          "Properties": null
        },
        "GoogleBigQuery": {
          "FriendlyName": null,
          "TablePartitionExpirationInDays": null,
          "TableExpirationInDays": null,
          "Collation": null,
          "CaseSensitive": null
        }
      }
    },
    "Tables": {
      "34898c53-6fc9-4067-ae4b-292affd3d47d": {
        "Id": "34898c53-6fc9-4067-ae4b-292affd3d47d",
        "TableId": "00000000-0000-0000-0000-000000000000",
        "Name": "DIM_SUPPLIER",
        "LogicalName": "DIM_SUPPLIER",
        "IsManyToMany": false,
        "SchemaId": null,
        "Generate": true,
        "PostScript": null,
        "Comment": null,
        "Color": null,
        "ColorOverride": false,
        "IsTransformationalModelingSource": true,
        "IsTransformationalModelingObject": null,
        "IsAutogeneratedName": false,
        "TemplateIds": [],
        "TableTemplateId": null,
        "TableType": 1,
        "LocationId": "306d9b28-186f-414a-bdb3-7833bb1634be",
        "Visibility": 1,
        "Columns": {
          "660a3505-901f-4f01-9f54-70d1b8fd8769": {
            "ColumnId": "660a3505-901f-4f01-9f54-70d1b8fd8769",
            "Name": "SUPPLIERID",
            "LogicalName": "SUPPLIERID",
            "DataType": "number(38,0)",
            "AllowNulls": false,
            "Position": 1,
            "Identity": false,
            "IdentityIncrement": null,
            "IdentitySeed": null,
            "DefaultName": null,
            "DefaultValue": null,
            "Comment": null,
            "Template": null,
            "SequenceId": null,
            "Visibility": 1,
            "SqlServer": {
              "Collation": null,
              "RowGuid": null,
              "Sparse": null,
              "FileStream": null,
              "ComputedExp": null,
              "Persisted": null
            },
            "MySql": {
              "GeneratedExp": null,
              "GeneratedStored": null,
              "Collation": null,
              "Unsigned": null,
              "ZeroFill": null,
              "ColumnFormat": null,
              "Storage": null
            },
            "Redshift": {
              "Encoding": null
            },
            "PostgreSql": {
              "Collation": null,
              "IdentityPrecedence": null,
              "IdentityMinValue": null,
              "IdentityMaxValue": null,
              "IdentityCache": null,
              "IdentityCycle": null
            },
            "AzureSynapse": {
              "Collation": null
            },
            "Snowflake": {
              "Collation": null,
              "Tags": {},
              "UseQuotes": false
            },
            "AlloyDb": {
              "Collation": null,
              "IdentityPrecedence": null,
              "IdentityMinValue": null,
              "IdentityMaxValue": null,
              "IdentityCache": null,
              "IdentityCycle": null
            },
            "Oracle": {
              "Collation": null,
              "Visible": null,
              "IdentityOptions": null
            },
            "Databricks": {
              "IdentityPrecedence": null,
              "Expression": null
            },
            "GoogleBigQuery": {
              "ParentId": null,
              "Collation": null,
              "RoundingMode": null
            },
            "IsAutogeneratedName": false,
            "DbtProperties": {}
          },
          "5f247561-8d35-441a-abf3-565540bc5c4d": {
            "ColumnId": "5f247561-8d35-441a-abf3-565540bc5c4d",
            "Name": "COMPANYNAME",
            "LogicalName": "COMPANYNAME",
            "DataType": "varchar(16777216)",
            "AllowNulls": false,
            "Position": 2,
            "Identity": false,
            "IdentityIncrement": null,
            "IdentitySeed": null,
            "DefaultName": null,
            "DefaultValue": null,
            "Comment": null,
            "Template": null,
            "SequenceId": null,
            "Visibility": 1,
            "SqlServer": {
              "Collation": null,
              "RowGuid": null,
              "Sparse": null,
              "FileStream": null,
              "ComputedExp": null,
              "Persisted": null
            },
            "MySql": {
              "GeneratedExp": null,
              "GeneratedStored": null,
              "Collation": null,
              "Unsigned": null,
              "ZeroFill": null,
              "ColumnFormat": null,
              "Storage": null
            },
            "Redshift": {
              "Encoding": null
            },
            "PostgreSql": {
              "Collation": null,
              "IdentityPrecedence": null,
              "IdentityMinValue": null,
              "IdentityMaxValue": null,
              "IdentityCache": null,
              "IdentityCycle": null
            },
            "AzureSynapse": {
              "Collation": null
            },
            "Snowflake": {
              "Collation": null,
              "Tags": {},
              "UseQuotes": false
            },
            "AlloyDb": {
              "Collation": null,
              "IdentityPrecedence": null,
              "IdentityMinValue": null,
              "IdentityMaxValue": null,
              "IdentityCache": null,
              "IdentityCycle": null
            },
            "Oracle": {
              "Collation": null,
              "Visible": null,
              "IdentityOptions": null
            },
            "Databricks": {
              "IdentityPrecedence": null,
              "Expression": null
            },
            "GoogleBigQuery": {
              "ParentId": null,
              "Collation": null,
              "RoundingMode": null
            },
            "IsAutogeneratedName": false,
            "DbtProperties": {}
          },
          "d981df9e-ffdf-4ea7-95df-991aad3ad0e5": {
            "ColumnId": "d981df9e-ffdf-4ea7-95df-991aad3ad0e5",
            "Name": "PHONE",
            "LogicalName": "PHONE",
            "DataType": "varchar(16777216)",
            "AllowNulls": true,
            "Position": 3,
            "Identity": false,
            "IdentityIncrement": null,
            "IdentitySeed": null,
            "DefaultName": null,
            "DefaultValue": null,
            "Comment": null,
            "Template": null,
            "SequenceId": null,
            "Visibility": 1,
            "SqlServer": {
              "Collation": null,
              "RowGuid": null,
              "Sparse": null,
              "FileStream": null,
              "ComputedExp": null,
              "Persisted": null
            },
            "MySql": {
              "GeneratedExp": null,
              "GeneratedStored": null,
              "Collation": null,
              "Unsigned": null,
              "ZeroFill": null,
              "ColumnFormat": null,
              "Storage": null
            },
            "Redshift": {
              "Encoding": null
            },
            "PostgreSql": {
              "Collation": null,
              "IdentityPrecedence": null,
              "IdentityMinValue": null,
              "IdentityMaxValue": null,
              "IdentityCache": null,
              "IdentityCycle": null
            },
            "AzureSynapse": {
              "Collation": null
            },
            "Snowflake": {
              "Collation": null,
              "Tags": {},
              "UseQuotes": false
            },
            "AlloyDb": {
              "Collation": null,
              "IdentityPrecedence": null,
              "IdentityMinValue": null,
              "IdentityMaxValue": null,
              "IdentityCache": null,
              "IdentityCycle": null
            },
            "Oracle": {
              "Collation": null,
              "Visible": null,
              "IdentityOptions": null
            },
            "Databricks": {
              "IdentityPrecedence": null,
              "Expression": null
            },
            "GoogleBigQuery": {
              "ParentId": null,
              "Collation": null,
              "RoundingMode": null
            },
            "IsAutogeneratedName": false,
            "DbtProperties": {}
          }
        },
        "Indexes": {
          "71daf3ea-7426-44b2-8fcf-c802f91809f4": {
            "IndexId": "71daf3ea-7426-44b2-8fcf-c802f91809f4",
            "Name": "PK_DIM_SUPPLIER",
            "IndexType": 1,
            "AsConstraint": true,
            "Columns": {
              "660a3505-901f-4f01-9f54-70d1b8fd8769": {
                "Id": "00000000-0000-0000-0000-000000000000",
                "ColumnId": "660a3505-901f-4f01-9f54-70d1b8fd8769",
                "Position": 1,
                "SortType": 1,
                "PkTableId": null,
                "PkColumnId": null,
                "RoleName": null,
                "PostgreSql": {
                  "Expression": null,
                  "Collation": null,
                  "OpClass": null,
                  "Nulls": null
                },
                "AlloyDb": {
                  "Expression": null,
                  "Collation": null,
                  "OpClass": null,
                  "Nulls": null
                },
                "Oracle": {
                  "Expression": null
                }
              }
            },
            "Generate": true,
            "Comment": null,
            "SnowflakeServer": {
              "UserExpression": false,
              "Expression": null,
              "Rely": false,
              "UseQuotes": false
            },
            "SqlServer": {
              "IsClustered": null,
              "Where": null,
              "IncludedColumns": {}
            },
            "MySql": {
              "ParserName": null,
              "StorageType": null,
              "KeyBlockSize": null
            },
            "PostgreSql": {
              "Only": null,
              "UsingMethod": null,
              "TableSpace": null,
              "Where": null,
              "Deferrable": null,
              "InitiallyDeferred": null,
              "FillFactor": null,
              "VacuumCleanupIndexScaleFactor": null,
              "Buffering": null,
              "FastUpdate": true,
              "GinPendingListLimit": null,
              "PagesPerRange": null,
              "AutoSummarize": null,
              "IncludedColumns": {},
              "PartitionType": null,
              "Partitions": {}
            },
            "Redshift": {
              "DistStyle": null,
              "SortKey": null
            },
            "AlloyDb": {
              "Only": null,
              "UsingMethod": null,
              "TableSpace": null,
              "Where": null,
              "Deferrable": null,
              "InitiallyDeferred": null,
              "FillFactor": null,
              "VacuumCleanupIndexScaleFactor": null,
              "Buffering": null,
              "FastUpdate": null,
              "GinPendingListLimit": null,
              "PagesPerRange": null,
              "AutoSummarize": null,
              "IncludedColumns": {}
            },
            "AzureSynapse": null,
            "Oracle": {
              "SortOptions": null,
              "UsableOptions": null,
              "VisibleOptions": null,
              "UserExpression": null,
              "Expression": null
            },
            "Databricks": {
              "Properties": null
            },
            "GoogleBigQuery": {
              "PartitionKeyOptions": null,
              "SearchIndexOptions": null
            }
          }
        },
        "References": {},
        "CheckConstraints": {},
        "DbtProperties": {},
        "MySql": null,
        "Snowflake": {
          "Transient": true,
          "DataRetentionTimeInDays": null,
          "FileFormatId": null,
          "OnError": null,
          "OnErrorSkipFileNumber": null,
          "OnErrorSkipFilePercent": null,
          "SizeLimit": null,
          "Purge": false,
          "ReturnFailedOnly": false,
          "TruncateColumns": false,
          "Force": false,
          "Tags": {},
          "UseQuotes": false,
          "SubType": null
        },
        "Redshift": null,
        "PostgreSql": null,
        "AzureSynapse": null,
        "AlloyDb": null,
        "Oracle": null,
        "Databricks": null,
        "GoogleBigQuery": null,
        "Logical": null
      }
    },
    "Domains": {},
    "SnowflakeFileFormats": {},
    "Views": {},
    "Templates": {},
    "TableTemplates": {},
    "Functions": {},
    "Procedures": {},
    "Sequences": {},
    "Tags": {},
    "GlobalTables": {},
    "GlobalViews": {},
    "GlobalFunctions": {},
    "GlobalProcedures": {}
  },
  "DiagramModel": {
    "SubjectAreas": {},
    "Diagrams": {
      "0741262f-0a96-44de-9b2d-c311c327fb87": {
        "DiagramId": "0741262f-0a96-44de-9b2d-c311c327fb87",
        "Name": "Main diagram",
        "SubjectAreaId": null,
        "Left": 0,
        "Top": 0,
        "Zoom": 100,
        "ActiveViewModeType": 4,
        "DiagramTables": {},
        "DisplayItems": {},
        "DiagramReferences": {},
        "DiagramViewModes": {},
        "DiagramViews": {},
        "DiagramFunctions": {},
        "DiagramProcedures": {},
        "comment": null,
        "DiagramDiscriminators": {}
      }
    },
    "ActiveSubjectAreaId": null,
    "ActiveDiagramId": "0741262f-0a96-44de-9b2d-c311c327fb87"
  },
  "NamingConvention": {
    "Standard": 0,
    "ObjectsNaming": {
      "SchemaTemplate": {
        "Template": "${SchemaName}",
        "UsedInGlossary": true,
        "IsEnabled": false
      },
      "SubjectAreaTemplate": {
        "Template": "${SubjectAreaName}",
        "UsedInGlossary": true,
        "IsEnabled": false
      },
      "TableTemplate": {
        "Template": "${TableName}",
        "UsedInGlossary": true,
        "IsEnabled": false
      },
      "ColumnTemplate": {
        "Template": "${ColumnName}",
        "UsedInGlossary": true,
        "IsEnabled": false
      },
      "PkTemplate": {
        "Template": "PK_${PkName}",
        "UsedInGlossary": true,
        "IsEnabled": false
      },
      "AkTemplate": {
        "Template": "AK_${AkName}",
        "UsedInGlossary": true,
        "IsEnabled": false
      },
      "CkName": {
        "Template": "CK_${CkName}",
        "UsedInGlossary": true,
        "IsEnabled": false
      },
      "KeyName": {
        "Template": null,
        "UsedInGlossary": true,
        "IsEnabled": false
      },
      "IndexTemplate": {
        "Template": "ind_${IdxName}",
        "UsedInGlossary": true,
        "IsEnabled": false
      },
      "FkIndexTemplate": {
        "Template": null,
        "UsedInGlossary": true,
        "IsEnabled": false
      },
      "RelTemplate": {
        "Template": "FK_${TableName}_${ParentTableName}",
        "UsedInGlossary": true,
        "IsEnabled": false
      },
      "VirtualRelTemplate": {
        "Template": "VFK_${VirtualRelName}",
        "UsedInGlossary": true,
        "IsEnabled": false
      },
      "CheckTemplate": {
        "Template": "check_${CheckName}",
        "UsedInGlossary": true,
        "IsEnabled": false
      },
      "ViewsTemplate": {
        "Template": null,
        "UsedInGlossary": true,
        "IsEnabled": false
      },
      "DomainTemplate": {
        "Template": null,
        "UsedInGlossary": true,
        "IsEnabled": false
      },
      "FileFormatTemplate": {
        "Template": "fileFormat_${FileFormatName}",
        "UsedInGlossary": true,
        "IsEnabled": false
      },
      "SequenceFormatTemplate": {
        "Template": "Seq_${SequenceName}",
        "UsedInGlossary": true,
        "IsEnabled": false
      },
      "PTKTemplate": {
        "Template": "PTK_${PartKeyName}",
        "UsedInGlossary": true,
        "IsEnabled": false
      },
      "PartitionTemplate": {
        "Template": "${TableName}",
        "UsedInGlossary": true,
        "IsEnabled": false
      },
      "BFTemplate": {
        "Template": "BF_${BloomFilterName}",
        "UsedInGlossary": true,
        "IsEnabled": false
      },
      "SITemplate": {
        "Template": "SI_${SearchIndexName}",
        "UsedInGlossary": true,
        "IsEnabled": false
      },
      "TagTemplate": {
        "Template": "${TagName}",
        "UsedInGlossary": true,
        "IsEnabled": false
      },
      "ExternalTableTemplate": {
        "Template": "${ExternalTableName}",
        "UsedInGlossary": true,
        "IsEnabled": false
      }
    },
    "Glossary": {},
    "ValidateOnSave": false
  },
  "SuggestedKeysPatterns": {
    "IncludeWords": [
      "key",
      "id",
      "pk",
      "code"
    ],
    "ExcludeWords": [
      "etl",
      "date",
      "name",
      "amount",
      "amt"
    ]
  },
  "DbtPropertiesSettings": {
    "access": {
      "Name": "access",
      "Template": null,
      "SelectItems": [
        {
          "Id": "e30533e2-cdc0-4e3b-8869-a6aa2e8573f9",
          "Value": "private"
        },
        {
          "Id": "3005f781-9ac8-4053-933c-7805c954f20b",
          "Value": "protected"
        },
        {
          "Id": "f6baf6a1-cfb7-4619-9c9f-920760a00fed",
          "Value": "public"
        }
      ],
      "Sources": null,
      "DefaultSelectedItemIds": null,
      "InputType": 3,
      "IsIncludedInDbtYaml": true,
      "ApplicableTo": [
        1
      ]
    },
    "docs": {
      "Name": "docs",
      "Template": "show: # true | false",
      "SelectItems": [],
      "Sources": null,
      "DefaultSelectedItemIds": null,
      "InputType": 2,
      "IsIncludedInDbtYaml": true,
      "ApplicableTo": [
        1
      ]
    },
    "external": {
      "Name": "external",
      "Template": "location: <string>\nfile_format: <string>\nrow_format: <string>\ntbl_properties: <string>      \npartitions: \n  - name: <string>\n    data_type: <string>\n    description: <string>\n    meta: <dictionary>\n  - ...\n<additional_property>: <additional_value>",
      "SelectItems": [],
      "Sources": null,
      "DefaultSelectedItemIds": null,
      "InputType": 2,
      "IsIncludedInDbtYaml": true,
      "ApplicableTo": [
        1
      ]
    },
    "freshness": {
      "Name": "freshness",
      "Template": "warn_after:\n  count:  <positive_integer>\n  period:  minute | hour | day\nerror_after:\n  count:  <positive_integer>\n  period: minute | hour | day\nfilter: <where-condition>",
      "SelectItems": [],
      "Sources": null,
      "DefaultSelectedItemIds": null,
      "InputType": 2,
      "IsIncludedInDbtYaml": true,
      "ApplicableTo": [
        1
      ]
    },
    "identifier": {
      "Name": "identifier",
      "Template": null,
      "SelectItems": [],
      "Sources": null,
      "DefaultSelectedItemIds": null,
      "InputType": 1,
      "IsIncludedInDbtYaml": true,
      "ApplicableTo": [
        1
      ]
    },
    "latest_version": {
      "Name": "latest_version",
      "Template": null,
      "SelectItems": [],
      "Sources": null,
      "DefaultSelectedItemIds": null,
      "InputType": 1,
      "IsIncludedInDbtYaml": true,
      "ApplicableTo": [
        1
      ]
    },
    "loaded_at_field": {
      "Name": "loaded_at_field",
      "Template": null,
      "SelectItems": [],
      "Sources": null,
      "DefaultSelectedItemIds": null,
      "InputType": 1,
      "IsIncludedInDbtYaml": true,
      "ApplicableTo": [
        1
      ]
    },
    "model_config": {
      "Name": "model_config",
      "Template": "enabled: true | false\ntags: <string> | [<string>]\npre-hook: <sql-statement> | [<sql-statement>]\npost-hook: <sql-statement> | [<sql-statement>]\ndatabase: <string>\nalias: <string>\npersist_docs: <string>\nfull_refresh: <string>\nmeta: {<dictionary>}\ngrants: {<dictionary>}\ncontract: {<dictionary>}",
      "SelectItems": [],
      "Sources": null,
      "DefaultSelectedItemIds": null,
      "InputType": 2,
      "IsIncludedInDbtYaml": true,
      "ApplicableTo": [
        1
      ]
    },
    "quote": {
      "Name": "quote",
      "Template": "# true | false",
      "SelectItems": [],
      "Sources": null,
      "DefaultSelectedItemIds": null,
      "InputType": 1,
      "IsIncludedInDbtYaml": true,
      "ApplicableTo": [
        2
      ]
    },
    "quoting": {
      "Name": "quoting",
      "Template": "database: true | false\nschema: true | false\nidentifier: true | false",
      "SelectItems": [],
      "Sources": null,
      "DefaultSelectedItemIds": null,
      "InputType": 2,
      "IsIncludedInDbtYaml": true,
      "ApplicableTo": [
        1
      ]
    },
    "source_table_config": {
      "Name": "source_table_config",
      "Template": "enabled: # true | false",
      "SelectItems": [],
      "Sources": null,
      "DefaultSelectedItemIds": null,
      "InputType": 2,
      "IsIncludedInDbtYaml": true,
      "ApplicableTo": [
        1
      ]
    },
    "sources": {
      "Name": "sources",
      "Template": null,
      "SelectItems": [
        {
          "Id": "283ce4eb-07d8-4a54-868e-9127490cf70b",
          "Value": "source_1"
        }
      ],
      "Sources": {
        "283ce4eb-07d8-4a54-868e-9127490cf70b": {
          "IsDefault": true,
          "Code": "description: #<markdown_string>\ndatabase: #<database_name>\nschema: #<schema_name>\nloader: #<string>\nloaded_at_field: #<column_name>\nmeta: #{<dictionary>}\ntags: #[<string>]\n\n# requires v1.1+\nconfig:\n  #<source_config>: <config_value>\n\noverrides: #<string>\n\nfreshness:\n  warn_after:\n    count: #<positive_integer>\n    period: #minute | hour | day\n  error_after:\n    count: #<positive_integer>\n    period: #minute | hour | day\n  filter: #<where-condition>\n\nquoting:\n  database: #true | false\n  schema: #true | false\n  identifier: #true | false"
        }
      },
      "DefaultSelectedItemIds": [
        "283ce4eb-07d8-4a54-868e-9127490cf70b"
      ],
      "InputType": 3,
      "IsIncludedInDbtYaml": true,
      "ApplicableTo": [
        1
      ]
    },
    "tags": {
      "Name": "tags",
      "Template": null,
      "SelectItems": [],
      "Sources": null,
      "DefaultSelectedItemIds": null,
      "InputType": 4,
      "IsIncludedInDbtYaml": true,
      "ApplicableTo": [
        1,
        2
      ]
    },
    "tests": {
      "Name": "tests",
      "Template": "- <test>\n- ... # declare additional tests",
      "SelectItems": [],
      "Sources": null,
      "DefaultSelectedItemIds": null,
      "InputType": 2,
      "IsIncludedInDbtYaml": true,
      "ApplicableTo": [
        1,
        2
      ]
    },
    "versions": {
      "Name": "versions",
      "Template": "- v: <version_identifier> # required",
      "SelectItems": [],
      "Sources": null,
      "DefaultSelectedItemIds": null,
      "InputType": 2,
      "IsIncludedInDbtYaml": true,
      "ApplicableTo": [
        1
      ]
    }
  }
}